zoop_wrapper/__init__.py
zoop_wrapper/_version.py
zoop_wrapper/constants.py
zoop_wrapper/exceptions.py
zoop_wrapper/response.py
zoop_wrapper/utils.py
zoop_wrapper/models/__init__.py
zoop_wrapper/models/bank_account.py
zoop_wrapper/models/base.py
zoop_wrapper/models/buyer.py
zoop_wrapper/models/card.py
zoop_wrapper/models/invoice.py
zoop_wrapper/models/seller.py
zoop_wrapper/models/token.py
zoop_wrapper/models/transaction.py
zoop_wrapper/models/utils.py
zoop_wrapper/models/webhook.py
zoop_wrapper/wrapper/__init__.py
zoop_wrapper/wrapper/bank_account.py
zoop_wrapper/wrapper/base.py
zoop_wrapper/wrapper/buyer.py
zoop_wrapper/wrapper/card.py
zoop_wrapper/wrapper/invoice.py
zoop_wrapper/wrapper/seller.py
zoop_wrapper/wrapper/transaction.py
zoop_wrapper/wrapper/webhook.py
zoop_wrapper-0.5.2.dist-info/LICENSE
zoop_wrapper-0.5.2.dist-info/METADATA
zoop_wrapper-0.5.2.dist-info/WHEEL
zoop_wrapper-0.5.2.dist-info/top_level.txt
zoop_wrapper-0.5.2.dist-info/RECORD
